datasci/__about__.py
datasci/__init__.py
datasci/tents.py
datasci_bricoletc-0.2.0.dist-info/METADATA
datasci_bricoletc-0.2.0.dist-info/WHEEL
datasci_bricoletc-0.2.0.dist-info/licenses/LICENSE
datasci_bricoletc-0.2.0.dist-info/RECORD
