Metadata-Version: 2.4
Name: datasci-bricoletc
Version: 0.2.0
Summary: Utilities for basic data science
Project-URL: Documentation, https://github.com/bricoletc/datasci#readme
Project-URL: Issues, https://github.com/bricoletc/datasci/issues
Project-URL: Source, https://github.com/bricoletc/datasci
Author-email: Brice Letcher <brice.letcher@ens-lyon.fr>
License-Expression: MIT
License-File: LICENSE
Classifier: Development Status :: 4 - Beta
Classifier: Programming Language :: Python
Classifier: Programming Language :: Python :: 3.7
Classifier: Programming Language :: Python :: 3.8
Classifier: Programming Language :: Python :: 3.9
Classifier: Programming Language :: Python :: 3.10
Classifier: Programming Language :: Python :: 3.11
Classifier: Programming Language :: Python :: Implementation :: CPython
Classifier: Programming Language :: Python :: Implementation :: PyPy
Requires-Python: >=3.7
